pobfuscatory/__init__.py
pobfuscatory/__main__.py
pobfuscatory/obfuscator.py
pobfuscatory-0.0.3.dist-info/LICENSE
pobfuscatory-0.0.3.dist-info/METADATA
pobfuscatory-0.0.3.dist-info/WHEEL
pobfuscatory-0.0.3.dist-info/top_level.txt
pobfuscatory-0.0.3.dist-info/RECORD
