Metadata-Version: 2.1
Name: pobfuscatory
Version: 0.0.3
Summary: python code obfuscator
Author-email: Rui-Cang Xie <birken1018@gmail.com>
Project-URL: Homepage, https://github.com/RayOct18/pobfuscatory
Project-URL: Bug Tracker, https://github.com/RayOct18/pobfuscatory/issues
Classifier: Programming Language :: Python :: 3
Classifier: License :: OSI Approved :: MIT License
Classifier: Operating System :: OS Independent
Requires-Python: >=3.6
License-File: LICENSE
Provides-Extra: test
Requires-Dist: pytest ; extra == 'test'
